README.md
setup.cfg
setup.py
Themer.egg-info/PKG-INFO
Themer.egg-info/SOURCES.txt
Themer.egg-info/dependency_links.txt
Themer.egg-info/requires.txt
Themer.egg-info/top_level.txt
scripts/themer
themer/__init__.py
themer/activators/__init__.py
themer/activators/acyl.py
themer/activators/i3.py
themer/activators/termite.py
themer/activators/wallfix.py
themer/parsers/__init__.py
themer/parsers/unsplash.py
themer/parsers/vim.py