Metadata-Version: 1.0
Name: Themer
Version: 1.8.3
Summary: Themer is a colorscheme generator and manager for your desktop.
Home-page: https://github.com/s-ol/themer
Author: Charles Leifer, Sol Bekic
Author-email: s+py@s-ol.nu
License: MIT
Keywords: wm colorscheme color theme wallpaper
Platform: UNKNOWN
